uber_central_client/__init__.py
uber_central_client/client.py
uber_central_client/exceptions.py
uber_central_client/models.py
uber_central_rest_client-1.2.0.dist-info/licenses/LICENSE
uber_central_rest_client-1.2.0.dist-info/METADATA
uber_central_rest_client-1.2.0.dist-info/WHEEL
uber_central_rest_client-1.2.0.dist-info/entry_points.txt
uber_central_rest_client-1.2.0.dist-info/top_level.txt
uber_central_rest_client-1.2.0.dist-info/RECORD
