Metadata-Version: 2.4
Name: uber-central-rest-client
Version: 1.2.0
Summary: Official Python client for the Uber Central API - Enterprise Uber ride management
Home-page: https://github.com/lymanlabs/uber-central
Author: Uber Central Team
Author-email: Uber Central Team <support@uber-central.com>
Maintainer-email: Uber Central Team <support@uber-central.com>
License: MIT
Project-URL: Homepage, https://github.com/lymanlabs/uber-central
Project-URL: Documentation, https://apparel-scraper--uber-central-api-serve.modal.run/docs
Project-URL: Repository, https://github.com/lymanlabs/uber-central
Project-URL: Issue Tracker, https://github.com/lymanlabs/uber-central/issues
Project-URL: API Endpoint, https://apparel-scraper--uber-central-api-serve.modal.run
Keywords: uber,ride,booking,api,client,transportation,enterprise,business,ride-sharing,mobility,travel,scheduling,fleet,corporate,expense,tracking
Classifier: Development Status :: 5 - Production/Stable
Classifier: Intended Audience :: Developers
Classifier: License :: OSI Approved :: MIT License
Classifier: Operating System :: OS Independent
Classifier: Programming Language :: Python :: 3
Classifier: Programming Language :: Python :: 3.8
Classifier: Programming Language :: Python :: 3.9
Classifier: Programming Language :: Python :: 3.10
Classifier: Programming Language :: Python :: 3.11
Classifier: Programming Language :: Python :: 3.12
Classifier: Topic :: Software Development :: Libraries :: Python Modules
Classifier: Topic :: Internet :: WWW/HTTP :: Dynamic Content
Classifier: Topic :: Office/Business
Classifier: Topic :: Communications
Classifier: Typing :: Typed
Requires-Python: >=3.8
License-File: LICENSE
Requires-Dist: requests>=2.25.0
Requires-Dist: pydantic<3.0.0,>=1.8.0
Requires-Dist: typing-extensions>=4.0.0; python_version < "3.10"
Provides-Extra: dev
Requires-Dist: pytest>=6.0.0; extra == "dev"
Requires-Dist: pytest-cov>=2.10.0; extra == "dev"
Requires-Dist: black>=21.0.0; extra == "dev"
Requires-Dist: flake8>=3.8.0; extra == "dev"
Requires-Dist: mypy>=0.800; extra == "dev"
Requires-Dist: twine>=3.0.0; extra == "dev"
Requires-Dist: build>=0.5.0; extra == "dev"
Provides-Extra: async
Requires-Dist: aiohttp>=3.7.0; extra == "async"
Requires-Dist: asyncio-throttle>=1.0.0; extra == "async"
Provides-Extra: testing
Requires-Dist: responses>=0.12.0; extra == "testing"
Requires-Dist: pytest-mock>=3.0.0; extra == "testing"
Requires-Dist: factory-boy>=3.0.0; extra == "testing"
Dynamic: author
Dynamic: home-page
Dynamic: license-file
Dynamic: requires-python
